uvn_fira/__init__.py
uvn_fira/api/__init__.py
uvn_fira/api/grid.py
uvn_fira/api/info.py
uvn_fira/api/player.py
uvn_fira/api/world.py
uvn_fira/core/__init__.py
uvn_fira/core/config.py
uvn_fira/core/data.py
uvn_fira/core/grid.py
uvn_fira/core/template.py
uvn_fira/core/vm.py
uvn_fira-1.3.1.dist-info/LICENSE.txt
uvn_fira-1.3.1.dist-info/WHEEL
uvn_fira-1.3.1.dist-info/METADATA
uvn_fira-1.3.1.dist-info/RECORD
