Metadata-Version: 2.1
Name: uvn-fira
Version: 1.3.1
Summary: The backend and API code for the Unscripted minigame.
Home-page: https://github.com/UnscriptedVN/fira
License: MPL-2.0
Author: Marquis Kurt
Author-email: software@marquiskurt.net
Requires-Python: >=2.7, !=3.0.*, !=3.1.*, !=3.2.*, !=3.3.*, !=3.4.*, !=3.5.*, !=3.6.*
Classifier: License :: OSI Approved
Classifier: Programming Language :: Python :: 2
Classifier: Programming Language :: Python :: 3
Classifier: Programming Language :: Python :: 3.7
Classifier: Programming Language :: Python :: 3.8
Classifier: Topic :: Games/Entertainment :: Puzzle Games
Classifier: Topic :: Software Development :: Libraries
Requires-Dist: toml (>=0.10.0,<0.11.0)
Requires-Dist: typing (>=3.7.4,<4.0.0)
Project-URL: Documentation, https://fira.marquiskurt.net
Project-URL: Repository, https://github.com/UnscriptedVN/fira
